pywrangle/__init__.py
pywrangle/missing_data.py
pywrangle/string_cleaning.py
pywrangle/data_errors/__init__.py
pywrangle/data_errors/constants.py
pywrangle/data_errors/converge_sim_vals.py
pywrangle/data_errors/identify_errors.py
pywrangle/data_errors/similarity_index.py
pywrangle/df_changes/__init__.py
pywrangle/df_changes/constants.py
pywrangle/df_changes/print_df_info.py
pywrangle/df_changes/record_df_info.py
pywrangle/print_tbl/__init__.py
pywrangle/print_tbl/custom_errors.py
pywrangle/print_tbl/script_objects.py
pywrangle/print_tbl/table_class.py
pywrangle/print_tbl/tblinfo_aux.py
pywrangle/print_tbl/tests.py
pywrangle/str_cleaning/__init__.py
pywrangle/str_cleaning/clean_all_strcol.py
pywrangle/str_cleaning/clean_strcol.py
pywrangle/str_cleaning/constants.py
tests/__init__.py
tests/context.py
tests/create_df.py
tests/test_clean_all_strcol.py
tests/test_clean_strcol.py
tests/test_converge_sim_vals.py
tests/test_identify_errors.py
tests/test_print_df_info.py
tests/test_record_df_info.py
pywrangle-0.3.0.dist-info/LICENSE
pywrangle-0.3.0.dist-info/METADATA
pywrangle-0.3.0.dist-info/WHEEL
pywrangle-0.3.0.dist-info/top_level.txt
pywrangle-0.3.0.dist-info/RECORD
