Metadata-Version: 2.1
Name: pywrangle
Version: 0.3.0
Summary: Auxiliary functions to clean pandas data frames
Home-page: https://github.com/jaimiles23/pywrangle
Author: Jai Miles
Author-email: jaimiles23@gmail.com
License: MIT
Keywords: clean,wrangle,pandas,dataframe,mangle
Platform: UNKNOWN
Requires-Python: >=3.8
Requires-Dist: pandas (>=1.0.3)
Requires-Dist: numpy (>=1.14.4)
Requires-Dist: fuzzywuzzy (==0.18.0)
Requires-Dist: python-levenshtein (==0.12.0)
Requires-Dist: metaphone (==0.6)
